yapfjunit/__init__.py
yapfjunit/cli.py
yapfjunit/junit_results.py
yapf_junit-0.25.0.dist-info/LICENSE
yapf_junit-0.25.0.dist-info/METADATA
yapf_junit-0.25.0.dist-info/WHEEL
yapf_junit-0.25.0.dist-info/entry_points.txt
yapf_junit-0.25.0.dist-info/top_level.txt
yapf_junit-0.25.0.dist-info/RECORD
