Metadata-Version: 2.1
Name: yapf-junit
Version: 0.25.0
Summary: Run yapf and report results in junit compatible xml
Home-page: https://github.com/dbradf/yapf-junit
Author: David Bradford
Author-email: david.bradford@mongodb.com
License: Apache License, Version 2.0
Platform: UNKNOWN
Classifier: Intended Audience :: Developers
Classifier: License :: OSI Approved :: Apache Software License
Classifier: Operating System :: OS Independent
Classifier: Programming Language :: Python :: 2
Classifier: Programming Language :: Python :: 3
Classifier: Programming Language :: Python :: Implementation :: CPython
Requires-Dist: click
Requires-Dist: yapf (==0.25.0)
